lto_cli/__init__.py
lto_cli/cli.py
lto_cli/config.py
lto_cli/handle_default.py
lto_cli/header.txt
lto_cli/commands/__init__.py
lto_cli/commands/account.py
lto_cli/commands/anchor.py
lto_cli/commands/association.py
lto_cli/commands/balance.py
lto_cli/commands/broadcast.py
lto_cli/commands/burn.py
lto_cli/commands/data.py
lto_cli/commands/leasing.py
lto_cli/commands/mass_transfer.py
lto_cli/commands/node.py
lto_cli/commands/script.py
lto_cli/commands/sponsorship.py
lto_cli/commands/transfer.py
lto_cli-1.2.8.dist-info/LICENSE
lto_cli-1.2.8.dist-info/METADATA
lto_cli-1.2.8.dist-info/WHEEL
lto_cli-1.2.8.dist-info/entry_points.txt
lto_cli-1.2.8.dist-info/top_level.txt
lto_cli-1.2.8.dist-info/RECORD
