Metadata-Version: 2.2
Name: lto-cli
Version: 1.2.8
Summary: LTO Network CLI
Home-page: https://github.com/ltonetwork/lto-cli
Author: LTO Network
Author-email: info@ltonetwork.com
Project-URL: Bug Tracker, https://github.com/ltonetwork/lto-cli/issues
Classifier: Programming Language :: Python :: 3
Classifier: License :: OSI Approved :: MIT License
Classifier: Operating System :: OS Independent
Requires-Python: >=3.6
License-File: LICENSE
Requires-Dist: lto==1.4.*
Requires-Dist: argparse
Requires-Dist: configparser
Requires-Dist: pathlib
Requires-Dist: setuptools
Requires-Dist: importlib-metadata~=4.8
